[
    {
        "x": "石油原油",
        "y": 21.96,
        "s": "百亿元"
    },
    {
        "x": "未烧结铁矿砂及其精矿",
        "y": 8.13,
        "s": "百亿元"
    },
    {
        "x": "铜矿砂及其精矿",
        "y": 3.9,
        "s": "百亿元"
    },
    {
        "x": "未梳的棉花",
        "y": 2.53,
        "s": "百亿元"
    },
    {
        "x": "高纯阴极铜（99.9999％＞铜含量＞99.9935％）                               ",
        "y": 2.14,
        "s": "百亿元"
    },
    {
        "x": "高纯阴极铜（铜含量≥99.9999％）                          ",
        "y": 2.14,
        "s": "百亿元"
    },
    {
        "x": "平均粒度大于6.3mm的未烧结铁矿砂及其精矿",
        "y": 2.07,
        "s": "百亿元"
    },
    {
        "x": "低硫的5-7号燃料油（硫含量不高于0.5%m/m）,不含生物柴油",
        "y": 1.45,
        "s": "百亿元"
    },
    {
        "x": "其他5-7号燃料油,不含生物柴油",
        "y": 1.45,
        "s": "百亿元"
    },
    {
        "x": "茂金属高密度聚乙烯（密度0.962g/cm^3，熔流率0.85g/10min）",
        "y": 1.31,
        "s": "百亿元"
    }
]